LICENSE
MANIFEST.in
README.md
setup.py
flask_gemoji/__init__.py
flask_gemoji.egg-info/PKG-INFO
flask_gemoji.egg-info/SOURCES.txt
flask_gemoji.egg-info/dependency_links.txt
flask_gemoji.egg-info/not-zip-safe
flask_gemoji.egg-info/top_level.txt
flask_gemoji/gemoji/images/emoji/+1.png
flask_gemoji/gemoji/images/emoji/-1.png
flask_gemoji/gemoji/images/emoji/100.png
flask_gemoji/gemoji/images/emoji/1234.png
flask_gemoji/gemoji/images/emoji/8ball.png
flask_gemoji/gemoji/images/emoji/a.png
flask_gemoji/gemoji/images/emoji/ab.png
flask_gemoji/gemoji/images/emoji/abc.png
flask_gemoji/gemoji/images/emoji/abcd.png
flask_gemoji/gemoji/images/emoji/accept.png
flask_gemoji/gemoji/images/emoji/aerial_tramway.png
flask_gemoji/gemoji/images/emoji/airplane.png
flask_gemoji/gemoji/images/emoji/alarm_clock.png
flask_gemoji/gemoji/images/emoji/alien.png
flask_gemoji/gemoji/images/emoji/ambulance.png
flask_gemoji/gemoji/images/emoji/anchor.png
flask_gemoji/gemoji/images/emoji/angel.png
flask_gemoji/gemoji/images/emoji/anger.png
flask_gemoji/gemoji/images/emoji/angry.png
flask_gemoji/gemoji/images/emoji/anguished.png
flask_gemoji/gemoji/images/emoji/ant.png
flask_gemoji/gemoji/images/emoji/apple.png
flask_gemoji/gemoji/images/emoji/aquarius.png
flask_gemoji/gemoji/images/emoji/aries.png
flask_gemoji/gemoji/images/emoji/arrow_backward.png
flask_gemoji/gemoji/images/emoji/arrow_double_down.png
flask_gemoji/gemoji/images/emoji/arrow_double_up.png
flask_gemoji/gemoji/images/emoji/arrow_down.png
flask_gemoji/gemoji/images/emoji/arrow_down_small.png
flask_gemoji/gemoji/images/emoji/arrow_forward.png
flask_gemoji/gemoji/images/emoji/arrow_heading_down.png
flask_gemoji/gemoji/images/emoji/arrow_heading_up.png
flask_gemoji/gemoji/images/emoji/arrow_left.png
flask_gemoji/gemoji/images/emoji/arrow_lower_left.png
flask_gemoji/gemoji/images/emoji/arrow_lower_right.png
flask_gemoji/gemoji/images/emoji/arrow_right.png
flask_gemoji/gemoji/images/emoji/arrow_right_hook.png
flask_gemoji/gemoji/images/emoji/arrow_up.png
flask_gemoji/gemoji/images/emoji/arrow_up_down.png
flask_gemoji/gemoji/images/emoji/arrow_up_small.png
flask_gemoji/gemoji/images/emoji/arrow_upper_left.png
