Metadata-Version: 1.0
Name: flask-gemoji
Version: 0.2.0
Summary: Add gemojis to your Flask apps
Home-page: https://github.com/marksteve/flask-gemoji
Author: Mark Steve Samson
Author-email: hello@marksteve.com
License: UNKNOWN
Platform: UNKNOWN
